brief_test/__init__.py
brief_test/core.py
brief_test/log.py
brief_test/server.py
brief_test-0.1.0.dist-info/METADATA
brief_test-0.1.0.dist-info/WHEEL
brief_test-0.1.0.dist-info/top_level.txt
brief_test-0.1.0.dist-info/RECORD
